huggingbutt/__init__.py
huggingbutt/agent.py
huggingbutt/env.py
huggingbutt/extend_error.py
huggingbutt/init.py
huggingbutt/logger_util.py
huggingbutt/network.py
huggingbutt/settings.py
huggingbutt/unity_gym_env_small_modified.py
huggingbutt/utils.py
huggingbutt-0.0.5.dist-info/LICENSE
huggingbutt-0.0.5.dist-info/METADATA
huggingbutt-0.0.5.dist-info/WHEEL
huggingbutt-0.0.5.dist-info/top_level.txt
huggingbutt-0.0.5.dist-info/RECORD
