Metadata-Version: 2.1
Name: huggingbutt
Version: 0.0.5
Summary: Client library to download and publish environments, agents on the huggingbutt.com hub
Author-email: huggingbutt <huggingbutt@outlook.com>
Project-URL: homepage, https://huggingbutt.com
Project-URL: source, https://github.com/huggingbutt/huggingbutt
Classifier: Programming Language :: Python :: 3
Classifier: Topic :: Scientific/Engineering :: Artificial Intelligence
Requires-Python: <=3.10.8,>=3.9.0
License-File: LICENSE
Requires-Dist: numpy ==1.21.2
Requires-Dist: grpcio <=1.48.2,>=1.11.0
Requires-Dist: protobuf <3.20,>=3.6
Requires-Dist: numpy <2.0,>=1.13.3
Requires-Dist: tqdm
Requires-Dist: requests
Requires-Dist: stable-baselines3 >=2.1.0
Requires-Dist: mlagents-envs ==0.30.0
Requires-Dist: tensorboard >=2.14
Requires-Dist: toml
Requires-Dist: pandas ==1.5.3
